LICENSE
MANIFEST.in
README.md
setup.cfg
setup.py
a3dj/__init__.py
a3dj.egg-info/PKG-INFO
a3dj.egg-info/SOURCES.txt
a3dj.egg-info/dependency_links.txt
a3dj.egg-info/not-zip-safe
a3dj.egg-info/requires.txt
a3dj.egg-info/top_level.txt
a3dj/core/__init__.py
a3dj/core/constant.py
a3dj/core/inner_errors.py
a3dj/core/request_utils.py
a3dj/core/response_utils.py
a3dj/core/utils.py
a3dj/core/factory_utils/__init__.py
a3dj/core/factory_utils/factory_generator.py
a3dj/core/factory_utils/factory_template.py
a3dj/core/factory_utils/field_template_translater.py
a3dj/core/factory_utils/field_templates.py
a3dj/core/factory_utils/text.py
a3dj/core/open_api_utils/__init__.py
a3dj/core/open_api_utils/open_api_doc_generator.py
a3dj/core/open_api_utils/view_open_api_util.py
a3dj/core/validators/__init__.py
a3dj/core/validators/file_validators.py
a3dj/errors/__init__.py
a3dj/errors/client_errors.py
a3dj/errors/error.py
a3dj/errors/server_errors.py
a3dj/locale/zh_Hans/LC_MESSAGES/django.mo
a3dj/locale/zh_Hans/LC_MESSAGES/django.po
a3dj/management/__init__.py
a3dj/management/commands/__init__.py
a3dj/management/commands/generate_factories.py
a3dj/management/commands/generate_open_api_doc.py
a3dj/middlewares/__init__.py
a3dj/middlewares/exception_middleware.py
a3dj/patches/__init__.py
a3dj/patches/patch_validation_error.py
a3dj/structs/__init__.py
a3dj/structs/base/__init__.py
a3dj/structs/base/base_field.py
a3dj/structs/base/struct.py
a3dj/structs/fields/__init__.py
a3dj/structs/fields/binary_field.py
a3dj/structs/fields/boolean_field.py
a3dj/structs/fields/char_field.py
a3dj/structs/fields/date_field.py
a3dj/structs/fields/datetime_field.py
a3dj/structs/fields/decimal_field.py
a3dj/structs/fields/duration_field.py
a3dj/structs/fields/email_field.py
a3dj/structs/fields/file_field.py
a3dj/structs/fields/float_field.py
a3dj/structs/fields/generic_ip_address_field.py
a3dj/structs/fields/image_field.py
a3dj/structs/fields/integer_field.py
a3dj/structs/fields/json_field.py
a3dj/structs/fields/list_field.py
a3dj/structs/fields/model_instance_field.py
a3dj/structs/fields/model_multiple_instance_field.py
a3dj/structs/fields/object_field.py
