Metadata-Version: 2.1
Name: a3dj
Version: 0.1.0
Summary: It is based on Django and can make development easier.
Home-page: https://gitee.com/three-kinds/a3dj
Author: three-kinds
Author-email: 3179158552@qq.com
License: Apache 2.0
Project-URL: Documentation, https://gitee.com/three-kinds/a3dj
Project-URL: Source, https://gitee.com/three-kinds/a3dj
Classifier: Development Status :: 2 - Pre-Alpha
Classifier: Environment :: Web Environment
Classifier: Intended Audience :: Developers
Classifier: License :: OSI Approved :: Apache Software License
Classifier: Operating System :: OS Independent
Classifier: Programming Language :: Python
Classifier: Programming Language :: Python :: 3
Classifier: Programming Language :: Python :: 3 :: Only
Classifier: Programming Language :: Python :: 3.8
Classifier: Programming Language :: Python :: 3.9
Classifier: Programming Language :: Python :: 3.10
Classifier: Programming Language :: Python :: 3.11
Classifier: Topic :: Internet :: WWW/HTTP
Classifier: Framework :: Django
Requires-Python: >=3.8
License-File: LICENSE
